azure_devtools/__init__.py
azure_devtools/ci_tools/__init__.py
azure_devtools/ci_tools/bot_framework.py
azure_devtools/ci_tools/git_tools.py
azure_devtools/ci_tools/github_tools.py
azure_devtools/scenario_tests/__init__.py
azure_devtools/scenario_tests/base.py
azure_devtools/scenario_tests/config.py
azure_devtools/scenario_tests/const.py
azure_devtools/scenario_tests/decorators.py
azure_devtools/scenario_tests/exceptions.py
azure_devtools/scenario_tests/patches.py
azure_devtools/scenario_tests/preparers.py
azure_devtools/scenario_tests/recording_processors.py
azure_devtools/scenario_tests/utilities.py
azure_devtools-1.2.0.dist-info/LICENSE
azure_devtools-1.2.0.dist-info/METADATA
azure_devtools-1.2.0.dist-info/WHEEL
azure_devtools-1.2.0.dist-info/top_level.txt
azure_devtools-1.2.0.dist-info/RECORD
