Metadata-Version: 2.1
Name: azure-devtools
Version: 1.2.0
Summary: Microsoft Azure Development Tools for SDK
Home-page: https://github.com/Azure/azure-python-devtools
Author: Microsoft Corporation
Author-email: ptvshelp@microsoft.com
License: MIT
Platform: UNKNOWN
Classifier: Development Status :: 3 - Alpha
Classifier: Intended Audience :: Developers
Classifier: Programming Language :: Python
Classifier: Programming Language :: Python :: 2
Classifier: Programming Language :: Python :: 2.7
Classifier: Programming Language :: Python :: 3
Classifier: Programming Language :: Python :: 3.4
Classifier: Programming Language :: Python :: 3.5
Classifier: Programming Language :: Python :: 3.6
Classifier: License :: OSI Approved :: MIT License
Provides-Extra: ci_tools
